LICENSE
enka/__init__.py
enka/client.py
enka/model/__init__.py
enka/model/_base.py
enka/model/user.py
py_enka-0.0.1.dist-info/LICENSE
py_enka-0.0.1.dist-info/WHEEL
py_enka-0.0.1.dist-info/METADATA
py_enka-0.0.1.dist-info/RECORD
